letras_custom_israelubeda/__init__.py
letras_custom_israelubeda/my_libreria.py
letras_custom_israelubeda-0.0.2.dist-info/METADATA
letras_custom_israelubeda-0.0.2.dist-info/WHEEL
letras_custom_israelubeda-0.0.2.dist-info/licenses/LICENSE
letras_custom_israelubeda-0.0.2.dist-info/RECORD
