Metadata-Version: 2.1
Name: letras_custom_israelubeda
Version: 0.0.2
Summary: Una libreria que transforma una letra por otra , ejemplo la letra A ,se transforma en letra Z
Project-URL: Homepage, https://github.com/israelubeda
Project-URL: Bug Tracker, https://github.com/israelubeda
Author-email: Israel Ubeda <israel.ubedabravo@gmail.com>
License-File: LICENSE
Classifier: License :: OSI Approved :: MIT License
Classifier: Operating System :: OS Independent
Classifier: Programming Language :: Python :: 3
Requires-Python: >=3.7
